advanced_math/__init__.py
advanced_math-0.0.5.dist-info/LICENSE.txt
advanced_math-0.0.5.dist-info/METADATA
advanced_math-0.0.5.dist-info/WHEEL
advanced_math-0.0.5.dist-info/top_level.txt
advanced_math-0.0.5.dist-info/RECORD
