Metadata-Version: 2.1
Name: advanced-math
Version: 0.0.5
Summary: module to handle advanced math operations
Home-page: https://github.com/vaibhavkrkm/advanced_math
Author: Vaibhav Kumar
Author-email: vaibhavkrkm@gmail.com
License: UNKNOWN
Platform: UNKNOWN
Classifier: Programming Language :: Python :: 3
Classifier: License :: OSI Approved :: MIT License
Classifier: Operating System :: OS Independent
